aa_timercog-0.0.4.dist-info/licenses/LICENSE
timercog/__init__.py
timercog/apps.py
timercog/auth_hooks.py
timercog/cogs/__init__.py
timercog/cogs/timer_cog.py
timercog/migrations/__init__.py
aa_timercog-0.0.4.dist-info/METADATA
aa_timercog-0.0.4.dist-info/WHEEL
aa_timercog-0.0.4.dist-info/top_level.txt
aa_timercog-0.0.4.dist-info/RECORD
