Metadata-Version: 2.4
Name: aa-timercog
Version: 0.0.4
Summary: Discord bot command extension for aa-structuretimers
Home-page: https://github.com/yourusername/aa-timercog
Author: crazydisi
Author-email: crazydisi <crazydisiofficial@gmail.com>
License: MIT
Project-URL: Homepage, https://github.com/crazydisi/aa-timercog
Project-URL: Repository, https://github.com/crazydisi/aa-timercog
Project-URL: Issues, https://github.com/crazydisi/aa-timercog/issues
Classifier: Environment :: Web Environment
Classifier: Framework :: Django
Classifier: Framework :: Django :: 4.2
Classifier: Intended Audience :: End Users/Desktop
Classifier: License :: OSI Approved :: MIT License
Classifier: Operating System :: OS Independent
Classifier: Programming Language :: Python
Classifier: Programming Language :: Python :: 3.10
Classifier: Programming Language :: Python :: 3.11
Classifier: Programming Language :: Python :: 3.12
Classifier: Topic :: Internet :: WWW/HTTP
Classifier: Topic :: Internet :: WWW/HTTP :: Dynamic Content
Requires-Python: >=3.10
License-File: LICENSE
Requires-Dist: allianceauth>=4.0.0
Requires-Dist: allianceauth-discordbot>=3.0.0
Requires-Dist: aa-structuretimers>=1.0.0
Requires-Dist: py-cord>=2.0.0
Provides-Extra: dev
Requires-Dist: black>=24.0.0; extra == "dev"
Requires-Dist: flake8>=7.0.0; extra == "dev"
Requires-Dist: isort>=5.13.0; extra == "dev"
Requires-Dist: pytest>=8.0.0; extra == "dev"
Requires-Dist: pytest-django>=4.7.0; extra == "dev"
Requires-Dist: pytest-cov>=4.1.0; extra == "dev"
Dynamic: author
Dynamic: home-page
Dynamic: license-file
Dynamic: requires-python
